evopreprocess/__init__.py
evopreprocess/data_sampling/EvoSampling.py
evopreprocess/data_sampling/SamplingBenchmark.py
evopreprocess/data_sampling/__init__.py
evopreprocess/data_weighting/EvoWeighting.py
evopreprocess/data_weighting/WeightingBenchmark.py
evopreprocess/data_weighting/__init__.py
evopreprocess/feature_selection/EvoFeatureSelection.py
evopreprocess/feature_selection/FeatureSelectionBenchmark.py
evopreprocess/feature_selection/__init__.py
evopreprocess/utils/EvoSettings.py
evopreprocess/utils/__init__.py
evopreprocess-0.5.0.dist-info/LICENSE
evopreprocess-0.5.0.dist-info/METADATA
evopreprocess-0.5.0.dist-info/WHEEL
evopreprocess-0.5.0.dist-info/top_level.txt
evopreprocess-0.5.0.dist-info/RECORD
