Metadata-Version: 2.1
Name: evopreprocess
Version: 0.5.0
Summary: Data Preprocessing with Evolutionary and Nature Inspired Algorithms.
Home-page: https://github.com/karakatic/EvoPreprocess
Author: Sašo Karakatič
Author-email: karakatic@gmail.com
License: GPLv3
Keywords: Evolutionary Algorithms,Nature Inspired Algorithms,Data Sampling,Instance Weighting,Feature Selection,Preprocessing,Machine Learning
Platform: UNKNOWN
Classifier: Programming Language :: Python :: 3
Classifier: Programming Language :: Python :: 3.5
Classifier: Programming Language :: Python :: 3.6
Classifier: Programming Language :: Python :: 3.7
Classifier: Programming Language :: Python :: 3.8
Classifier: Programming Language :: Python :: 3.9
Classifier: Programming Language :: Python :: 3.10
Classifier: License :: OSI Approved :: GNU General Public License v3 (GPLv3)
Classifier: Operating System :: OS Independent
Classifier: Development Status :: 5 - Production/Stable
Classifier: Intended Audience :: Science/Research
Classifier: Intended Audience :: Developers
Classifier: Natural Language :: English
Classifier: Topic :: Software Development
Classifier: Topic :: Scientific/Engineering
Classifier: Topic :: Scientific/Engineering :: Artificial Intelligence
Classifier: Topic :: Scientific/Engineering :: Information Analysis
Requires-Dist: numpy
Requires-Dist: scipy
Requires-Dist: scikit-learn
Requires-Dist: imbalanced-learn
Requires-Dist: NiaPy (>=2.0.4)
